{
  "schema": "flowmetrics.cfd.v1",
  "command": "cfd",
  "generated_at": "2026-05-16T10:24:32.746974-06:00",
  "headline": "CFD for astral-sh/uv Apr 16, 2026 \u2192 May 15, 2026: 589 items arrived, 203 completed, 386 still in flight at end.",
  "definition": "Stacked-area chart of items by workflow step over time. The top line counts every item that has ever entered the system; the bottom line counts items finished. The vertical gap at any sample date is items still in flight (WIP). Includes carry-over items that were already open at window start AND items still open at window end \u2014 so the chart shows real WIP, not just items that both arrived and finished inside the window.",
  "summary": {
    "workflow": [
      "Open",
      "Merged"
    ],
    "samples": 30,
    "arrivals_at_end": 589,
    "departures_at_end": 203,
    "wip_at_start": 349,
    "wip_at_end": 386,
    "peak_wip": 386
  },
  "key_insight": "The largest WIP band at May 15, 2026 is 'Open' with 386 items in flight. The thicker that band is on the chart, the more work is queued or in-progress at that stage; the steeper the line bordering it, the faster items are arriving into the stage.",
  "next_actions": [
    "Investigate why items accumulate in 'Open'. Either items are arriving faster than this stage can process, or they're waiting on a downstream resource (reviewers, environments, decisions).",
    "Look for places where one line flattens \u2014 that's a stall in that band.",
    "Compare band widths to the previous window to spot accumulation trends."
  ],
  "caveats": [
    "Past data only \u2014 the chart does not project forward.",
    "Items still in flight may be under-represented when the source only fetches completed work. Wider bands today may grow tomorrow.",
    "Workflow used: Open \u2192 Merged. Items that visit statuses outside this list are silently skipped at those points."
  ],
  "vocabulary": {
    "Cumulative Flow Diagram": "Stacked area chart of cumulative counts per workflow state over time. Each state's line counts items that have entered that state or any later one \u2014 so the lines never cross and never decrease.",
    "Arrivals": "Top line of a CFD. Cumulative count of items that have entered the workflow (first state) by each sample date. Slope = arrival rate.",
    "Departures": "Bottom line of a CFD. Cumulative count of items that have exited the workflow (last state) by each sample date. Slope = throughput.",
    "WIP": "Work In Progress. Vertical distance between two adjacent CFD lines at a sample date = items currently in that workflow band. Per (see DECISIONS.md for the math).",
    "Workflow state": "A named stage in your delivery process (e.g., Open, In Progress, Done). CFDs require an ordered list \u2014 earliest stage to latest."
  },
  "chart_data": {
    "points": [
      {
        "sampled_on": "2026-04-16",
        "counts_by_state": {
          "Open": 351,
          "Merged": 2
        }
      },
      {
        "sampled_on": "2026-04-17",
        "counts_by_state": {
          "Open": 361,
          "Merged": 11
        }
      },
      {
        "sampled_on": "2026-04-18",
        "counts_by_state": {
          "Open": 362,
          "Merged": 12
        }
      },
      {
        "sampled_on": "2026-04-19",
        "counts_by_state": {
          "Open": 365,
          "Merged": 13
        }
      },
      {
        "sampled_on": "2026-04-20",
        "counts_by_state": {
          "Open": 394,
          "Merged": 37
        }
      },
      {
        "sampled_on": "2026-04-21",
        "counts_by_state": {
          "Open": 406,
          "Merged": 55
        }
      },
      {
        "sampled_on": "2026-04-22",
        "counts_by_state": {
          "Open": 411,
          "Merged": 59
        }
      },
      {
        "sampled_on": "2026-04-23",
        "counts_by_state": {
          "Open": 420,
          "Merged": 66
        }
      },
      {
        "sampled_on": "2026-04-24",
        "counts_by_state": {
          "Open": 426,
          "Merged": 68
        }
      },
      {
        "sampled_on": "2026-04-25",
        "counts_by_state": {
          "Open": 429,
          "Merged": 69
        }
      },
      {
        "sampled_on": "2026-04-26",
        "counts_by_state": {
          "Open": 431,
          "Merged": 69
        }
      },
      {
        "sampled_on": "2026-04-27",
        "counts_by_state": {
          "Open": 459,
          "Merged": 92
        }
      },
      {
        "sampled_on": "2026-04-28",
        "counts_by_state": {
          "Open": 460,
          "Merged": 93
        }
      },
      {
        "sampled_on": "2026-04-29",
        "counts_by_state": {
          "Open": 472,
          "Merged": 107
        }
      },
      {
        "sampled_on": "2026-04-30",
        "counts_by_state": {
          "Open": 476,
          "Merged": 113
        }
      },
      {
        "sampled_on": "2026-05-01",
        "counts_by_state": {
          "Open": 481,
          "Merged": 113
        }
      },
      {
        "sampled_on": "2026-05-02",
        "counts_by_state": {
          "Open": 483,
          "Merged": 114
        }
      },
      {
        "sampled_on": "2026-05-03",
        "counts_by_state": {
          "Open": 484,
          "Merged": 115
        }
      },
      {
        "sampled_on": "2026-05-04",
        "counts_by_state": {
          "Open": 495,
          "Merged": 128
        }
      },
      {
        "sampled_on": "2026-05-05",
        "counts_by_state": {
          "Open": 510,
          "Merged": 140
        }
      },
      {
        "sampled_on": "2026-05-06",
        "counts_by_state": {
          "Open": 518,
          "Merged": 144
        }
      },
      {
        "sampled_on": "2026-05-07",
        "counts_by_state": {
          "Open": 526,
          "Merged": 150
        }
      },
      {
        "sampled_on": "2026-05-08",
        "counts_by_state": {
          "Open": 531,
          "Merged": 153
        }
      },
      {
        "sampled_on": "2026-05-09",
        "counts_by_state": {
          "Open": 535,
          "Merged": 155
        }
      },
      {
        "sampled_on": "2026-05-10",
        "counts_by_state": {
          "Open": 541,
          "Merged": 158
        }
      },
      {
        "sampled_on": "2026-05-11",
        "counts_by_state": {
          "Open": 559,
          "Merged": 174
        }
      },
      {
        "sampled_on": "2026-05-12",
        "counts_by_state": {
          "Open": 569,
          "Merged": 184
        }
      },
      {
        "sampled_on": "2026-05-13",
        "counts_by_state": {
          "Open": 573,
          "Merged": 189
        }
      },
      {
        "sampled_on": "2026-05-14",
        "counts_by_state": {
          "Open": 581,
          "Merged": 197
        }
      },
      {
        "sampled_on": "2026-05-15",
        "counts_by_state": {
          "Open": 589,
          "Merged": 203
        }
      }
    ],
    "bands": [
      {
        "sampled_on": "2026-04-16",
        "state": "Open",
        "wip_in_state": 349,
        "entered_at_or_later": 351
      },
      {
        "sampled_on": "2026-04-16",
        "state": "Merged",
        "wip_in_state": 2,
        "entered_at_or_later": 2
      },
      {
        "sampled_on": "2026-04-17",
        "state": "Open",
        "wip_in_state": 350,
        "entered_at_or_later": 361
      },
      {
        "sampled_on": "2026-04-17",
        "state": "Merged",
        "wip_in_state": 11,
        "entered_at_or_later": 11
      },
      {
        "sampled_on": "2026-04-18",
        "state": "Open",
        "wip_in_state": 350,
        "entered_at_or_later": 362
      },
      {
        "sampled_on": "2026-04-18",
        "state": "Merged",
        "wip_in_state": 12,
        "entered_at_or_later": 12
      },
      {
        "sampled_on": "2026-04-19",
        "state": "Open",
        "wip_in_state": 352,
        "entered_at_or_later": 365
      },
      {
        "sampled_on": "2026-04-19",
        "state": "Merged",
        "wip_in_state": 13,
        "entered_at_or_later": 13
      },
      {
        "sampled_on": "2026-04-20",
        "state": "Open",
        "wip_in_state": 357,
        "entered_at_or_later": 394
      },
      {
        "sampled_on": "2026-04-20",
        "state": "Merged",
        "wip_in_state": 37,
        "entered_at_or_later": 37
      },
      {
        "sampled_on": "2026-04-21",
        "state": "Open",
        "wip_in_state": 351,
        "entered_at_or_later": 406
      },
      {
        "sampled_on": "2026-04-21",
        "state": "Merged",
        "wip_in_state": 55,
        "entered_at_or_later": 55
      },
      {
        "sampled_on": "2026-04-22",
        "state": "Open",
        "wip_in_state": 352,
        "entered_at_or_later": 411
      },
      {
        "sampled_on": "2026-04-22",
        "state": "Merged",
        "wip_in_state": 59,
        "entered_at_or_later": 59
      },
      {
        "sampled_on": "2026-04-23",
        "state": "Open",
        "wip_in_state": 354,
        "entered_at_or_later": 420
      },
      {
        "sampled_on": "2026-04-23",
        "state": "Merged",
        "wip_in_state": 66,
        "entered_at_or_later": 66
      },
      {
        "sampled_on": "2026-04-24",
        "state": "Open",
        "wip_in_state": 358,
        "entered_at_or_later": 426
      },
      {
        "sampled_on": "2026-04-24",
        "state": "Merged",
        "wip_in_state": 68,
        "entered_at_or_later": 68
      },
      {
        "sampled_on": "2026-04-25",
        "state": "Open",
        "wip_in_state": 360,
        "entered_at_or_later": 429
      },
      {
        "sampled_on": "2026-04-25",
        "state": "Merged",
        "wip_in_state": 69,
        "entered_at_or_later": 69
      },
      {
        "sampled_on": "2026-04-26",
        "state": "Open",
        "wip_in_state": 362,
        "entered_at_or_later": 431
      },
      {
        "sampled_on": "2026-04-26",
        "state": "Merged",
        "wip_in_state": 69,
        "entered_at_or_later": 69
      },
      {
        "sampled_on": "2026-04-27",
        "state": "Open",
        "wip_in_state": 367,
        "entered_at_or_later": 459
      },
      {
        "sampled_on": "2026-04-27",
        "state": "Merged",
        "wip_in_state": 92,
        "entered_at_or_later": 92
      },
      {
        "sampled_on": "2026-04-28",
        "state": "Open",
        "wip_in_state": 367,
        "entered_at_or_later": 460
      },
      {
        "sampled_on": "2026-04-28",
        "state": "Merged",
        "wip_in_state": 93,
        "entered_at_or_later": 93
      },
      {
        "sampled_on": "2026-04-29",
        "state": "Open",
        "wip_in_state": 365,
        "entered_at_or_later": 472
      },
      {
        "sampled_on": "2026-04-29",
        "state": "Merged",
        "wip_in_state": 107,
        "entered_at_or_later": 107
      },
      {
        "sampled_on": "2026-04-30",
        "state": "Open",
        "wip_in_state": 363,
        "entered_at_or_later": 476
      },
      {
        "sampled_on": "2026-04-30",
        "state": "Merged",
        "wip_in_state": 113,
        "entered_at_or_later": 113
      },
      {
        "sampled_on": "2026-05-01",
        "state": "Open",
        "wip_in_state": 368,
        "entered_at_or_later": 481
      },
      {
        "sampled_on": "2026-05-01",
        "state": "Merged",
        "wip_in_state": 113,
        "entered_at_or_later": 113
      },
      {
        "sampled_on": "2026-05-02",
        "state": "Open",
        "wip_in_state": 369,
        "entered_at_or_later": 483
      },
      {
        "sampled_on": "2026-05-02",
        "state": "Merged",
        "wip_in_state": 114,
        "entered_at_or_later": 114
      },
      {
        "sampled_on": "2026-05-03",
        "state": "Open",
        "wip_in_state": 369,
        "entered_at_or_later": 484
      },
      {
        "sampled_on": "2026-05-03",
        "state": "Merged",
        "wip_in_state": 115,
        "entered_at_or_later": 115
      },
      {
        "sampled_on": "2026-05-04",
        "state": "Open",
        "wip_in_state": 367,
        "entered_at_or_later": 495
      },
      {
        "sampled_on": "2026-05-04",
        "state": "Merged",
        "wip_in_state": 128,
        "entered_at_or_later": 128
      },
      {
        "sampled_on": "2026-05-05",
        "state": "Open",
        "wip_in_state": 370,
        "entered_at_or_later": 510
      },
      {
        "sampled_on": "2026-05-05",
        "state": "Merged",
        "wip_in_state": 140,
        "entered_at_or_later": 140
      },
      {
        "sampled_on": "2026-05-06",
        "state": "Open",
        "wip_in_state": 374,
        "entered_at_or_later": 518
      },
      {
        "sampled_on": "2026-05-06",
        "state": "Merged",
        "wip_in_state": 144,
        "entered_at_or_later": 144
      },
      {
        "sampled_on": "2026-05-07",
        "state": "Open",
        "wip_in_state": 376,
        "entered_at_or_later": 526
      },
      {
        "sampled_on": "2026-05-07",
        "state": "Merged",
        "wip_in_state": 150,
        "entered_at_or_later": 150
      },
      {
        "sampled_on": "2026-05-08",
        "state": "Open",
        "wip_in_state": 378,
        "entered_at_or_later": 531
      },
      {
        "sampled_on": "2026-05-08",
        "state": "Merged",
        "wip_in_state": 153,
        "entered_at_or_later": 153
      },
      {
        "sampled_on": "2026-05-09",
        "state": "Open",
        "wip_in_state": 380,
        "entered_at_or_later": 535
      },
      {
        "sampled_on": "2026-05-09",
        "state": "Merged",
        "wip_in_state": 155,
        "entered_at_or_later": 155
      },
      {
        "sampled_on": "2026-05-10",
        "state": "Open",
        "wip_in_state": 383,
        "entered_at_or_later": 541
      },
      {
        "sampled_on": "2026-05-10",
        "state": "Merged",
        "wip_in_state": 158,
        "entered_at_or_later": 158
      },
      {
        "sampled_on": "2026-05-11",
        "state": "Open",
        "wip_in_state": 385,
        "entered_at_or_later": 559
      },
      {
        "sampled_on": "2026-05-11",
        "state": "Merged",
        "wip_in_state": 174,
        "entered_at_or_later": 174
      },
      {
        "sampled_on": "2026-05-12",
        "state": "Open",
        "wip_in_state": 385,
        "entered_at_or_later": 569
      },
      {
        "sampled_on": "2026-05-12",
        "state": "Merged",
        "wip_in_state": 184,
        "entered_at_or_later": 184
      },
      {
        "sampled_on": "2026-05-13",
        "state": "Open",
        "wip_in_state": 384,
        "entered_at_or_later": 573
      },
      {
        "sampled_on": "2026-05-13",
        "state": "Merged",
        "wip_in_state": 189,
        "entered_at_or_later": 189
      },
      {
        "sampled_on": "2026-05-14",
        "state": "Open",
        "wip_in_state": 384,
        "entered_at_or_later": 581
      },
      {
        "sampled_on": "2026-05-14",
        "state": "Merged",
        "wip_in_state": 197,
        "entered_at_or_later": 197
      },
      {
        "sampled_on": "2026-05-15",
        "state": "Open",
        "wip_in_state": 386,
        "entered_at_or_later": 589
      },
      {
        "sampled_on": "2026-05-15",
        "state": "Merged",
        "wip_in_state": 203,
        "entered_at_or_later": 203
      }
    ]
  },
  "input": {
    "repo": "astral-sh/uv",
    "start": "2026-04-16",
    "stop": "2026-05-15",
    "workflow": [
      "Open",
      "Merged"
    ],
    "interval_days": 1,
    "offline": false
  },
  "docs": {
    "metrics": "docs/METRICS.md",
    "forecast": "docs/FORECAST.md",
    "decisions": "docs/DECISIONS.md"
  },
  "cli_invocation": "uv run flow cfd --repo astral-sh/uv --start 2026-04-16 --stop 2026-05-15 --workflow 'Open,Merged' --interval-days 1",
  "logs": []
}
